zmsgcentre.py
zmsgcentre-2.0.1.dist-info/LICENSE
zmsgcentre-2.0.1.dist-info/METADATA
zmsgcentre-2.0.1.dist-info/WHEEL
zmsgcentre-2.0.1.dist-info/top_level.txt
zmsgcentre-2.0.1.dist-info/RECORD
