Metadata-Version: 2.1
Name: zmsgcentre
Version: 2.0.1
Summary: 消息中心, 避免代码的强耦合性, 支持多线程
Home-page: https://pypi.org/
Author: zlyuan
Author-email: 1277260932@qq.com
License: GNU GENERAL PUBLIC LICENSE
Platform: all
Classifier: Environment :: Web Environment
Classifier: Intended Audience :: Developers
Classifier: Operating System :: OS Independent
Classifier: Programming Language :: Python :: 3
